nchr/__init__.py
nchr/_modidx.py
nchr/core.py
nchr/escd.py
nchr/tree.py
nchr/type.py
nchr-0.0.11.dist-info/LICENSE
nchr-0.0.11.dist-info/METADATA
nchr-0.0.11.dist-info/WHEEL
nchr-0.0.11.dist-info/entry_points.txt
nchr-0.0.11.dist-info/top_level.txt
nchr-0.0.11.dist-info/RECORD
